deephaven_ib/__init__.py
deephaven_ib/time.py
deephaven_ib/_internal/__init__.py
deephaven_ib/_internal/error_codes.py
deephaven_ib/_internal/short_rates.py
deephaven_ib/_internal/tablewriter.py
deephaven_ib/_internal/threading.py
deephaven_ib/_internal/trace.py
deephaven_ib/_tws/__init__.py
deephaven_ib/_tws/contract_registry.py
deephaven_ib/_tws/ib_type_logger.py
deephaven_ib/_tws/order_id_queue.py
deephaven_ib/_tws/requests.py
deephaven_ib/_tws/tws_client.py
deephaven_ib-0.6.2.dist-info/licenses/LICENSE
deephaven_ib-0.6.2.dist-info/METADATA
deephaven_ib-0.6.2.dist-info/WHEEL
deephaven_ib-0.6.2.dist-info/top_level.txt
deephaven_ib-0.6.2.dist-info/RECORD
