Metadata-Version: 2.4
Name: deephaven_ib
Version: 0.6.2
Summary: An Interactive Brokers integration for Deephaven
Home-page: https://github.com/deephaven-examples/deephaven-ib
Author: David R. (Chip) Kent IV
Author-email: chipkent@deephaven.io
Project-URL: Deephaven, https://deephaven.io
Project-URL: Deephaven GitHub, https://github.com/deephaven/deephaven-core
Project-URL: GitHub Issues, https://github.com/deephaven-examples/deephaven-ib/issues
Classifier: Programming Language :: Python :: 3
Classifier: License :: OSI Approved :: Apache Software License
Classifier: Operating System :: OS Independent
Classifier: Intended Audience :: Developers
Classifier: Intended Audience :: End Users/Desktop
Classifier: Intended Audience :: Financial and Insurance Industry
Classifier: Topic :: Database :: Database Engines/Servers
Classifier: Topic :: Office/Business :: Financial :: Investment
Classifier: Topic :: Software Development :: Libraries :: Python Modules
Requires-Python: >=3.10
License-File: LICENSE
Requires-Dist: deephaven-server
Requires-Dist: pandas
Requires-Dist: ibapi==10.19.04
Requires-Dist: lxml
Requires-Dist: ratelimit
Dynamic: author
Dynamic: author-email
Dynamic: classifier
Dynamic: description
Dynamic: description-content-type
Dynamic: home-page
Dynamic: license-file
Dynamic: project-url
Dynamic: requires-dist
Dynamic: requires-python
Dynamic: summary
